aprodaku/__init__.py
aprodaku/filters.py
aprodaku-0.1.4.dist-info/DESCRIPTION.rst
aprodaku-0.1.4.dist-info/METADATA
aprodaku-0.1.4.dist-info/RECORD
aprodaku-0.1.4.dist-info/WHEEL
aprodaku-0.1.4.dist-info/metadata.json
aprodaku-0.1.4.dist-info/top_level.txt
