Metadata-Version: 2.0
Name: aprodaku
Version: 0.1.4
Summary: Steveroku/steveda via apache
Home-page: https://github.com/FoleyDiver/aprodaku
Author: Steve Foley
Author-email: sfoley1988@gmail.com
License: GPLv2+
Download-URL: https://github.com/FoleyDiver/aprodaku/archive/v0.1.4.tar.gz
Platform: UNKNOWN
Classifier: Development Status :: 3 - Alpha
Classifier: License :: OSI Approved :: GNU General Public License v2 or later (GPLv2+)
Classifier: Intended Audience :: Developers
Classifier: Programming Language :: Python :: 3.4
Classifier: Programming Language :: Python :: 3.5
Classifier: Programming Language :: Python :: 3.6
Requires-Dist: steov
